liuli/__init__.py
liuli/cyliuli.cp37-win_amd64.pyd
liuli/liuli.py
liuli/tokenizer.py
liuli/vocab.py
liuli-0.0.1.dist-info/LICENSE
liuli-0.0.1.dist-info/METADATA
liuli-0.0.1.dist-info/WHEEL
liuli-0.0.1.dist-info/top_level.txt
liuli-0.0.1.dist-info/RECORD
