Metadata-Version: 2.1
Name: liuli
Version: 0.0.1
Summary: liuli is better than jieba.
Home-page: https://github.com/lixiepeng/liuli
Author: Xiepeng Li
Author-email: phiedulxp@gmail.com
License: MIT
Platform: UNKNOWN
Classifier: Programming Language :: Python :: 2
Classifier: Programming Language :: Python :: 3
Requires-Dist: jieba
